{"name":"Novo painel","layout":{"id":"model00000179bed084ba_00000000","items":[{"id":"model00000179bed084bb_00000000","items":[{"id":"model00000179bed084bb_00000001","css":"templateBox aspectRatio_default","items":[{"id":"model00000179bed084bb_00000002","style":{"top":"0%","left":"0%","right":"50%","bottom":"50%"},"type":"templateDropZone","templateName":"dz1","relatedLayouts":""},{"id":"model00000179bed084bc_00000000","css":"noBorderLeft","style":{"top":"0%","left":"50%","right":"0%","bottom":"50%"},"type":"templateDropZone","templateName":"dz2","relatedLayouts":""},{"id":"model00000179bed084bc_00000001","css":"noBorderTop","style":{"top":"50%","left":"0%","right":"50%","bottom":"0%"},"type":"templateDropZone","templateName":"dz3"},{"id":"model00000179bed084bc_00000002","css":"noBorderLeft noBorderTop","style":{"top":"50%","left":"50%","right":"0%","bottom":"0%"},"type":"templateDropZone","templateName":"dz4"},{"id":"model00000179bee235c8_00000000","style":{"left":"28.00237056883902%","top":"4.1862899005756145%","height":"41.99811616954474%","width":"71.99767346847467%"},"type":"widget","relatedLayouts":"","content":{}},{"id":"model00000179bedf7918_00000000","style":{"left":"0%","top":"5%","height":"40%","width":"30%"},"type":"widget","relatedLayouts":"","content":{}},{"id":"model00000179bed292da_00000000","style":{"left":"0%","top":"0.3504799823358089%","height":"14.019199293432356%","width":"86.1159191720059%"},"type":"widget","relatedLayouts":"","clones":1,"content":{}},{"id":"model00000179bee74fd7_00000000","style":{"left":"0%","top":"50%","height":"49.99999823699722%","width":"99.99870017274705%"},"type":"widget","relatedLayouts":"","content":{}},{"id":"model00000179bed50bab_00000000","from":"model00000179bed292da_00000000","style":{"left":"0%","top":"43.809997791976116%","height":"14.019199293432356%","width":"66.94805322819123%"},"type":"widget","relatedLayouts":"","clones":0,"content":{}}],"type":"genericPage","layoutPositioning":"relative"}],"type":"container","title":{"translationTable":{"Default":"Visão Geral"}},"templateName":"Template9"},{"id":"model00000179bed63b70_00000000","items":[{"id":"model00000179bed63b70_00000001","css":"templateBox aspectRatio_default","items":[{"id":"model00000179bed63b70_00000002","style":{"top":"0%","left":"0%","right":"50%","bottom":"75%"},"type":"templateDropZone","templateName":"dz1","relatedLayouts":""},{"id":"model00000179bed63b71_00000000","css":"noBorderLeft","style":{"top":"0%","left":"50%","right":"0%","bottom":"75%"},"type":"templateDropZone","templateName":"dz3"},{"id":"model00000179bed63b71_00000001","css":"noBorderTop","style":{"top":"25%","left":"0%","right":"50%","bottom":"37.5%"},"type":"templateDropZone","templateName":"dz4"},{"id":"model00000179bed63b71_00000002","css":"noBorderTop","style":{"top":"62.5%","left":"0%","right":"50%","bottom":"0%"},"type":"templateDropZone","templateName":"dz5"},{"id":"model00000179bed63b71_00000003","css":"noBorderLeft noBorderTop","style":{"top":"25%","left":"50%","right":"0%","bottom":"0%"},"type":"templateDropZone","templateName":"dz2"},{"id":"model00000179bf020a50_00000002","style":{"left":"0%","top":"7.078313253012048%","height":"25%","width":"20.087848598827556%"},"type":"widget","relatedLayouts":"","content":{}},{"id":"model00000179bf02eb4a_00000000","style":{"left":"21.98618011535606%","top":"10.490693739424703%","height":"37.68510998307952%","width":"60.02626920221575%"},"type":"widget","relatedLayouts":"","content":{}},{"id":"model00000179bf0436f0_00000000","style":{"left":"0%","top":"54.653130287648054%","height":"35.45634517766498%","width":"80.29924047741419%"},"type":"widget","relatedLayouts":"","content":{}},{"id":"model00000179bed92e65_00000000","style":{"left":"21.98618011535606%","top":"0%","height":"14%","width":"58.186663620962065%"},"type":"widget","relatedLayouts":"","clones":2,"content":{}},{"id":"model00000179bedc00f2_00000000","from":"model00000179bed92e65_00000000","style":{"left":"0%","top":"48.05414551607445%","height":"13.999052453468694%","width":"51.136047817562286%"},"type":"widget","relatedLayouts":"","clones":0,"content":{}},{"id":"model00000179bf0d9c34_00000000","from":"model00000179bed92e65_00000000","style":{"left":"0%","top":"0%","height":"8.87847891566265%","width":"21.898614076107215%"},"type":"widget","relatedLayouts":"","clones":0,"content":{}}],"type":"genericPage","layoutPositioning":"relative"}],"type":"container","title":{"translationTable":{"Default":"Visão Produto"}},"templateName":"Template6"}],"style":{"height":"100%"},"type":"tab","showGrid":false,"snapGrid":true,"snapObjects":true,"pageSize":{"height":720,"width":1280},"layoutPositioning":"relative","fitPage":true},"theme":"defaultTheme","version":1601,"eventGroups":[{"id":"model00000179bed084bb_00000000:1","widgetIds":["model00000179bed292da_00000000","model00000179bed50bab_00000000","model00000179bedf7918_00000000","model00000179bee235c8_00000000","model00000179bee74fd7_00000000"]},{"id":"model00000179bed63b70_00000000:1","widgetIds":["model00000179bed92e65_00000000","model00000179bedc00f2_00000000","model00000179bf020a50_00000002","model00000179bf02eb4a_00000000","model00000179bf0436f0_00000000"]}],"properties":{"customColors":{"colors":["#1D2473","#595859","#343334"]},"defaultLocale":"Default","fredIsRed":true},"drillThrough":[],"fredIsRed":{"id":"model00000179bed084b8_00000000","colorMap":{"-599.9000":{"v":0,"s":2},"105.0000":{"v":1,"s":2},"1219.1200":{"v":2,"s":2},"229.0000":{"v":3,"s":2},"255.0000":{"v":4,"s":2},"2980.6400":{"v":5,"s":2},"359.0000":{"v":6,"s":2},"379.0000":{"v":7,"s":2},"39.0000":{"v":8,"s":2},"479.9000":{"v":9,"s":2},"599.0000":{"v":10,"s":2},"599.9000":{"v":11,"s":2},"699.9000":{"v":12,"s":2},"749.9000":{"v":13,"s":2},"849.9000":{"v":14,"s":2},"99.0000":{"v":15,"s":2},"valorvendaunidade (Contagem distinta)":{"v":16,"s":2},"datacompra (Contar)":{"v":17,"s":2}},"saveId":2},"pageContext":[{"origin":"filter","table":"","alias":"0","sourceId":"model00000179bedabade_00000001","scope":"global","hierarchyNames":["idlojista"],"hierarchyUniqueNames":["compra_produto_csv.idlojista"],"exclude":false,"isNamedSet":false,"tupleSet":"{\"compra_produto_csv.idlojista->[37450]\":{\"u\":\"compra_produto_csv.idlojista->[37450]\",\"d\":\"37450\"}}"},{"origin":"filter","table":"","alias":"0","sourceId":"model00000179bedabade_00000001","conditions":[],"scope":"global","hierarchyNames":["pub"],"hierarchyUniqueNames":["compra_produto_csv.pub"],"isNamedSet":false},{"origin":"visualization","table":"","alias":"0","sourceId":"model00000179bedabade_00000001","hierarchies":[{"hierarchyUniqueName":"compra_produto_csv.idskureferencia"}],"scope":"model00000179bed63b70_00000000","hierarchyUniqueNames":["compra_produto_csv.idskureferencia"],"eventSourceId":"model00000179bf020a50_00000002","eventGroupId":"model00000179bed63b70_00000000:1","tupleSet":"{\"compra_produto_csv.idskureferencia->[3185594]\":{\"u\":\"compra_produto_csv.idskureferencia->[3185594]\",\"d\":\"3185594\"}}"}],"dataSources":{"version":"1.0","sources":[{"id":"model00000179bedabade_00000001","assetId":"assetId00000179bedabadc_00000000","clientId":"de02faf2-fbe4-466f-b8cd-44296f096a9d:010ee671-73a7-4475-b2fc-ff24fc1e3c78:010ee671-73a7-4475-b2fc-ff24fc1e3c78:data_asset:compra_produto.csv","module":{"xsd":"https://ibm.com/daas/module/1.0/module.xsd","source":{"id":"de02faf2-fbe4-466f-b8cd-44296f096a9d:010ee671-73a7-4475-b2fc-ff24fc1e3c78:010ee671-73a7-4475-b2fc-ff24fc1e3c78:data_asset:compra_produto.csv","srcUrl":{"sourceUrl":"{enc}TheBLUhsxOoeT08n/qo+GRCWvX4/Gu3xxv58mMxnUZ0sB5vhVrmAImEIHAhi93XGDFFxRu7w3cylMTvGxwIHqsWuM8Tu2zAALqKYDgo+HZtrfQV6EF/fJ2QPRp7brrxnZXa/nxyCVVFTVkz7YahebVXQW0ym0vj/49eXDNwYi3xNfixGItG2PXasehYz46Dptjl7amyjbvZTNural+/4S2TP/yT34F5yLx053yVIUPw82zzkqalMtLC4difgdo1Kpne8gwqTZ3Z9/8xSBDmnFNMHxcukNYfXzxp4ZsSEvVMfFmFyOX03t7lcKYKNDefcKughsk0yoDF04S35S6kp8g==","mimeType":"text/csv","property":[{"name":"headers","value":[{"name":"Authorization","value":"{enc}OPd1GEKnILaw06JBbFxj2RaBJeHW4vi576IEYO8EIwlwYSrWSkjPvCLZii0LhTWO9Dh/LUt3lwXDnGsiQf0ZlGh9uQT3eP0jKlilGxmlVcUi2mpsJnP4Bt20UcOlmf0Mv6dwKfb4RiuJF6NXpx0n/0/ROzcW67B0Ywp24CTewKJ9venndZo5ecPh/JA5D07rPsrJ7WmOI/9pAEYvH7HeIwDgW1mqmn1mZeMnwkHkGYGtIsJSJ/ifi/ByWTFweIYYg09UTCezhRGJ1uRDYzBlKp743wDSPlgUzXSlHngmOUznABZFmmpr0hS3xWfH+h3RuMj9gcbM3disg+uwfqSSEA=="}]}]}},"table":{"column":[{"datatype":"BIGINT","name":"pub","label":"pub","description":"pub","usage":"fact","regularAggregate":"total","taxonomyFamily":"cNone","nullable":true},{"datatype":"NVARCHAR(MAX)","name":"idskureferencia","label":"idskureferencia","description":"idskureferencia","usage":"attribute","regularAggregate":"countDistinct","taxonomyFamily":"cNone","nullable":true},{"datatype":"NVARCHAR(MAX)","name":"idlojista","label":"idlojista","description":"idlojista","usage":"attribute","regularAggregate":"countDistinct","taxonomyFamily":"cNone","nullable":true},{"datatype":"NVARCHAR(MAX)","name":"estado","label":"estado","description":"estado","usage":"attribute","regularAggregate":"countDistinct","taxonomyFamily":"cNone","nullable":true},{"datatype":"NVARCHAR(MAX)","name":"idcompraentrega","label":"idcompraentrega","description":"idcompraentrega","usage":"attribute","regularAggregate":"countDistinct","taxonomyFamily":"cNone","nullable":true},{"datatype":"NVARCHAR(MAX)","name":"iddepartamento","label":"iddepartamento","description":"iddepartamento","usage":"attribute","regularAggregate":"countDistinct","taxonomyFamily":"cNone","nullable":true},{"datatype":"NVARCHAR(MAX)","name":"nomedepartamento","label":"nomedepartamento","description":"nomedepartamento","usage":"attribute","regularAggregate":"countDistinct","taxonomyFamily":"cNone","nullable":true},{"datatype":"NVARCHAR(MAX)","name":"idsetor","label":"idsetor","description":"idsetor","usage":"attribute","regularAggregate":"countDistinct","taxonomyFamily":"cNone","nullable":true},{"datatype":"NVARCHAR(MAX)","name":"nomesetor","label":"nomesetor","description":"nomesetor","usage":"attribute","regularAggregate":"countDistinct","taxonomyFamily":"cNone","nullable":true},{"datatype":"DATE","name":"datacompra","label":"datacompra","description":"datacompra","usage":"attribute","regularAggregate":"countDistinct","taxonomyFamily":"cNone","nullable":true},{"datatype":"NVARCHAR(MAX)","name":"diff_dias","label":"diff_dias","description":"diff_dias","usage":"attribute","regularAggregate":"countDistinct","taxonomyFamily":"cNone","nullable":true},{"datatype":"NVARCHAR(MAX)","name":"idsku","label":"idsku","description":"idsku","usage":"attribute","regularAggregate":"countDistinct","taxonomyFamily":"cNone","nullable":true},{"datatype":"NVARCHAR(MAX)","name":"valorvendaunidade","label":"valorvendaunidade","description":"valorvendaunidade","usage":"attribute","regularAggregate":"countDistinct","taxonomyFamily":"cNone","nullable":true},{"datatype":"DOUBLE","name":"valorfrete","label":"valorfrete","description":"valorfrete","usage":"fact","regularAggregate":"total","taxonomyFamily":"cNone","nullable":true}],"name":"compra_produto_csv","label":"compra_produto.csv"},"id":"de02faf2-fbe4-466f-b8cd-44296f096a9d:010ee671-73a7-4475-b2fc-ff24fc1e3c78:010ee671-73a7-4475-b2fc-ff24fc1e3c78:data_asset:compra_produto.csv","label":"compra_produto.csv","identifier":"compra_produto_csv"},"name":"compra_produto.csv","shaping":{"embeddedModuleUpToDate":true}}]},"widgets":{"model00000179bed292da_00000000":{"id":"model00000179bed292da_00000000","type":"text","name":{"translationTable":{"Default":"Quantidade total de vendas colocadas no período"}},"content":{"translationTable":{"Default":"<div class=\"staticContent textFillNoScroll\" dir=\"auto\" style=\"\"><div class=\"summernote\" style=\"display: none;\"></div><div class=\"note-editor\"><div class=\"note-dropzone\">  <div class=\"note-dropzone-message\"></div></div><div class=\"note-editing-area\"><div class=\"note-handle\"><div class=\"note-control-selection\"><div class=\"note-control-selection-bg\"></div><div class=\"note-control-holder note-control-nw\"></div><div class=\"note-control-holder note-control-ne\"></div><div class=\"note-control-holder note-control-sw\"></div><div class=\"note-control-sizing note-control-se\"></div><div class=\"note-control-selection-info\"></div></div></div><div class=\"note-editable\" contenteditable=\"false\" id=\"model00000179bed292da_00000000Editable\"><span class=\"textFitted responsiveColor responsiveFontSize responsiveFontFamily\" style=\"overflow-wrap: normal; font-size: 0.1px;\"><p><b><span class=\"color9\">﻿</span><span class=\"color9\">Quantidade total de vendas colocadas no período</span></b></p></span></div></div></div></div>"}},"isResponsive":true,"placeholder":{"showIcon":false,"text":"Digite seu texto aqui"},"visTypeLocked":true},"model00000179bed50bab_00000000":{"id":"model00000179bed50bab_00000000","type":"text","name":{"translationTable":{"Default":"Quantidade de vendas por departamento"}},"content":{"translationTable":{"Default":"<div class=\"staticContent textFillNoScroll\" dir=\"auto\" style=\"\"><div class=\"summernote\" style=\"display: none;\"></div><div class=\"note-editor\"><div class=\"note-dropzone\">  <div class=\"note-dropzone-message\"></div></div><div class=\"note-editing-area\"><div class=\"note-handle\"><div class=\"note-control-selection\"><div class=\"note-control-selection-bg\"></div><div class=\"note-control-holder note-control-nw\"></div><div class=\"note-control-holder note-control-ne\"></div><div class=\"note-control-holder note-control-sw\"></div><div class=\"note-control-sizing note-control-se\"></div><div class=\"note-control-selection-info\"></div></div></div><div class=\"note-editable\" contenteditable=\"false\" id=\"model00000179bed50bab_00000000Editable\"><span class=\"textFitted responsiveColor responsiveFontSize responsiveFontFamily\" style=\"overflow-wrap: normal; font-size: 0.1px;\"><p><font color=\"#498313\"><b>Quantidade de vendas por departamento</b></font></p></span></div></div></div></div>"}},"isResponsive":true,"placeholder":{"showIcon":false,"text":"Digite seu texto aqui"},"visTypeLocked":true},"model00000179bed92e65_00000000":{"id":"model00000179bed92e65_00000000","type":"text","name":{"translationTable":{"Default":"Quantidade de vendas por produto"}},"content":{"translationTable":{"Default":"<div class=\"staticContent textFillNoScroll\" dir=\"auto\" style=\"\"><div class=\"summernote\" style=\"display: none;\"></div><div class=\"note-editor\"><div class=\"note-dropzone\">  <div class=\"note-dropzone-message\"></div></div><div class=\"note-editing-area\"><div class=\"note-handle\"><div class=\"note-control-selection\"><div class=\"note-control-selection-bg\"></div><div class=\"note-control-holder note-control-nw\"></div><div class=\"note-control-holder note-control-ne\"></div><div class=\"note-control-holder note-control-sw\"></div><div class=\"note-control-sizing note-control-se\"></div><div class=\"note-control-selection-info\"></div></div></div><div class=\"note-editable\" contenteditable=\"false\" id=\"model00000179bed92e65_00000000Editable\"><span class=\"textFitted responsiveColor responsiveFontSize responsiveFontFamily\" style=\"overflow-wrap: normal; font-size: 15px;\"><p><span class=\"color9\"><b>Quantidade de vendas por produto</b></span></p></span></div></div></div></div>"}},"isResponsive":true,"placeholder":{"showIcon":false,"text":"Digite seu texto aqui"},"visTypeLocked":true},"model00000179bedc00f2_00000000":{"id":"model00000179bedc00f2_00000000","type":"text","name":{"translationTable":{"Default":"Variação de preço do produto"}},"content":{"translationTable":{"Default":"<div class=\"staticContent textFillNoScroll\" dir=\"auto\" style=\"\"><div class=\"summernote\" style=\"display: none;\"></div><div class=\"note-editor\"><div class=\"note-dropzone\">  <div class=\"note-dropzone-message\"></div></div><div class=\"note-editing-area\"><div class=\"note-handle\"><div class=\"note-control-selection\"><div class=\"note-control-selection-bg\"></div><div class=\"note-control-holder note-control-nw\"></div><div class=\"note-control-holder note-control-ne\"></div><div class=\"note-control-holder note-control-sw\"></div><div class=\"note-control-sizing note-control-se\"></div><div class=\"note-control-selection-info\"></div></div></div><div class=\"note-editable\" contenteditable=\"false\" id=\"model00000179bedc00f2_00000000Editable\"><span class=\"textFitted responsiveColor responsiveFontSize responsiveFontFamily\" style=\"overflow-wrap: normal; font-size: 55px;\"><p style=\"text-align: center;\"><font color=\"#498313\"><b>Variação de preço do produto</b></font></p></span></div></div></div></div>"}},"isResponsive":true,"placeholder":{"showIcon":false,"text":"Digite seu texto aqui"},"visTypeLocked":true},"model00000179bedf7918_00000000":{"type":"live","id":"model00000179bedf7918_00000000","visId":"summary","name":{"translationTable":{}},"data":{"dataViews":[{"modelRef":"model00000179bedabade_00000001","dataItems":[{"id":"id91706036","itemId":"compra_produto_csv.idlojista","itemLabel":"idlojista","aggregate":"count","navigationPathId":null}],"id":"model00000179bedf7917_00000000"}]},"visTypeLocked":true,"slotmapping":{"slots":[{"name":"actual","dataItems":["id91706036"],"dataItemSettings":[],"layerId":"data"}]},"properties":[{"id":"elementColor","value":"color11"},{"id":"baseValueLabel","value":{"translationTable":{"Default":"Vendas"}}}],"localFilters":[]},"model00000179bee235c8_00000000":{"type":"live","id":"model00000179bee235c8_00000000","visId":"com.ibm.vis.rave2line","name":{"translationTable":{}},"data":{"dataViews":[{"modelRef":"model00000179bedabade_00000001","dataItems":[{"id":"id1980269687","itemId":"compra_produto_csv.datacompra","itemLabel":"datacompra","format":{"formatSpec":{"type":"date","timezone":"America/New_York","locale":"pt","dateStyle":"short","local":true}},"navigationPathId":null},{"id":"id387166160","itemId":"compra_produto_csv.idcompraentrega","itemLabel":"idcompraentrega","aggregate":"count","navigationPathId":null}],"id":"model00000179bee235c7_00000000"}]},"visTypeLocked":true,"slotmapping":{"slots":[{"name":"categories","dataItems":["id1980269687"],"dataItemSettings":[],"layerId":"data"},{"name":"values","dataItems":["id387166160"],"dataItemSettings":[],"layerId":"data"}]},"properties":[],"localFilters":[]},"model00000179bee74fd7_00000000":{"type":"live","id":"model00000179bee74fd7_00000000","visId":"com.ibm.vis.rave2bundlebar","name":{"translationTable":{}},"data":{"dataViews":[{"modelRef":"model00000179bedabade_00000001","dataItems":[{"id":"id1622256940","itemId":"compra_produto_csv.nomedepartamento","itemLabel":"nomedepartamento","selection":[]},{"id":"id_2050148963","itemId":"compra_produto_csv.nomesetor","itemLabel":"nomesetor","navigationPathId":null},{"id":"id91706036","itemId":"compra_produto_csv.idlojista","itemLabel":"idlojista","selection":[{"operation":"order","sort":{"type":"desc","priority":1,"by":"caption","custom":{}}}],"aggregate":"count","navigationPathId":null}],"id":"model00000179bee77d61_00000000"}]},"visTypeLocked":true,"slotmapping":{"slots":[{"name":"categories","dataItems":["id1622256940","id_2050148963"],"dataItemSettings":[],"layerId":"data"},{"name":"values","dataItems":["id91706036"],"dataItemSettings":[],"layerId":"data"}]},"properties":[],"localFilters":[]},"model00000179bf020a50_00000002":{"type":"live","id":"model00000179bf020a50_00000002","visId":"list","name":{"translationTable":{}},"data":{"dataViews":[{"modelRef":"model00000179bedabade_00000001","dataItems":[{"id":"id_165650139","itemId":"compra_produto_csv.idskureferencia","itemLabel":"idskureferencia","navigationPathId":null}],"id":"model00000179bf020a50_00000000"}]},"slotmapping":{"slots":[{"name":"level1","dataItems":["id_165650139"],"layerId":"data"}]},"properties":[],"localFilters":[]},"model00000179bf02eb4a_00000000":{"type":"live","id":"model00000179bf02eb4a_00000000","visId":"com.ibm.vis.rave2bundlecolumn","name":{"translationTable":{}},"data":{"dataViews":[{"modelRef":"model00000179bedabade_00000001","dataItems":[{"id":"id1980269687","itemId":"compra_produto_csv.datacompra","itemLabel":"datacompra","format":{"formatSpec":{"type":"date","timezone":"America/New_York","locale":"pt","dateStyle":"short","local":true}}},{"id":"id_165650139","itemId":"compra_produto_csv.idskureferencia","itemLabel":"idskureferencia","aggregate":"count"}],"id":"model00000179bf039f19_00000000"}]},"visTypeLocked":true,"slotmapping":{"slots":[{"name":"categories","dataItems":["id1980269687"],"dataItemSettings":[],"layerId":"data"},{"name":"values","dataItems":["id_165650139"],"dataItemSettings":[],"layerId":"data"}]},"properties":[],"localFilters":[]},"model00000179bf0436f0_00000000":{"type":"live","id":"model00000179bf0436f0_00000000","visId":"com.ibm.vis.rave2line","name":{"translationTable":{}},"data":{"dataViews":[{"modelRef":"model00000179bedabade_00000001","dataItems":[{"id":"id1980269687","itemId":"compra_produto_csv.datacompra","itemLabel":"datacompra"},{"id":"id1073037287","itemId":"compra_produto_csv.valorvendaunidade","itemLabel":"valorvendaunidade"}],"id":"model00000179bf04be6e_00000000"}]},"visTypeLocked":true,"slotmapping":{"slots":[{"name":"categories","dataItems":["id1980269687"],"layerId":"data"},{"name":"values","dataItems":["id1073037287"],"dataItemSettings":[],"layerId":"data"}]},"properties":[],"localFilters":[]},"model00000179bf0d9c34_00000000":{"id":"model00000179bf0d9c34_00000000","type":"text","name":{"translationTable":{"Default":"Selecione um produto:"}},"content":{"translationTable":{"Default":"<div class=\"staticContent textFillNoScroll\" dir=\"auto\" style=\"\"><div class=\"summernote\" style=\"display: none;\"></div><div class=\"note-editor\"><div class=\"note-dropzone\">  <div class=\"note-dropzone-message\"></div></div><div class=\"note-editing-area\"><div class=\"note-handle\"><div class=\"note-control-selection\" style=\"display: none;\"><div class=\"note-control-selection-bg\"></div><div class=\"note-control-holder note-control-nw\"></div><div class=\"note-control-holder note-control-ne\"></div><div class=\"note-control-holder note-control-sw\"></div><div class=\"note-control-sizing note-control-se\"></div><div class=\"note-control-selection-info\"></div></div></div><div class=\"note-editable\" contenteditable=\"false\" id=\"model00000179bf0d9c34_00000000Editable\"><span class=\"textFitted responsiveColor responsiveFontSize responsiveFontFamily\" style=\"overflow-wrap: normal; font-size: 22px;\"><p><span class=\"color9\"><b>Selecione um produto:</b></span></p></span></div></div></div></div>"}},"isResponsive":true,"placeholder":{"showIcon":false,"text":"Digite seu texto aqui"},"visTypeLocked":true}}}